{
  "name": "Bucks County CuriARTsity",
  "url": "",
  "tagline": "Fine Art & Curious Antiques",
  "description": "A curated collection of fine art, antiques, and wonderfully unexpected finds in the heart of Lambertville, NJ.",
  "address": {
    "locatedWithin": "Darberry's Antiques",
    "street": "80 Lambert Ln",
    "city": "Lambertville",
    "state": "NJ",
    "zip": "08530"
  },
  "phone": "(908) 329-4446",
  "email": "hello@bccuriartsity.com",
  "hours": [
    { "days": "Sunday", "time": "11:00 AM - 5:00 PM" },
    { "days": "Monday", "time": "11:00 AM - 4:00 PM" },
    { "days": "Tuesday - Thursday", "time": "Closed" },
    { "days": "Friday", "time": "11:00 AM - 4:00 PM" },
    { "days": "Saturday", "time": "11:00 AM - 5:00 PM" }
  ],
  "hoursSchema": [
    { "days": ["Sunday", "Saturday"], "opens": "11:00", "closes": "17:00" },
    { "days": ["Monday", "Friday"], "opens": "11:00", "closes": "16:00" }
  ],
  "social": {
    "instagram": "https://www.instagram.com/buckscountycuriartsity",
    "chairish": "https://www.chairish.com/shop/buckscountycuriartsity"
  },
  "maps": {
    "apple": "https://maps.apple.com/place?q=Darberry%27s%20Antiques&auid=1397877729542252910&address=80%20Lambert%20Ln,%20Lambertville,%20NJ%20%2008530,%20United%20States&ll=40.3684354,-74.94773",
    "google": "https://www.google.com/maps/place/?q=place_id:ChIJGSeNGRL_w4kRX_IX-uurq0M",
    "waze": "https://waze.com/ul?ll=40.3684354,-74.94773&navigate=yes"
  }
}
